llm_chunker/__init__.py
llm_chunker/analyzer.py
llm_chunker/core.py
llm_chunker/fuzzy_match.py
llm_chunker/prompt_builder.py
llm_chunker/prompts.py
llm_chunker/text_utils.py
llm_chunker-0.2.0.dist-info/licenses/LICENSE
llm_chunker-0.2.0.dist-info/METADATA
llm_chunker-0.2.0.dist-info/WHEEL
llm_chunker-0.2.0.dist-info/top_level.txt
llm_chunker-0.2.0.dist-info/RECORD
