Metadata-Version: 2.4
Name: llm-chunker
Version: 0.2.0
Summary: Add your description here
Home-page: https://github.com/Theeojeong/llm-chunker
Author: Theeojeong
Author-email: wogusto13@gmail.com
Requires-Python: >=3.9
License-File: LICENSE
Requires-Dist: nltk>=3.6
Requires-Dist: openai>=1.0.0
Requires-Dist: python-dotenv>=1.2.1
Dynamic: author
Dynamic: author-email
Dynamic: home-page
Dynamic: license-file
Dynamic: requires-python
